code_splitter-0.1.5.dist-info/METADATA
code_splitter-0.1.5.dist-info/WHEEL
code_splitter/__init__.py
code_splitter/code_splitter.pypy39-pp73-aarch64-linux-gnu.so
code_splitter-0.1.5.dist-info/RECORD
