Metadata-Version: 2.3
Name: code-splitter
Version: 0.1.5
Classifier: Programming Language :: Rust
Classifier: Programming Language :: Python :: Implementation :: CPython
Classifier: Programming Language :: Python :: Implementation :: PyPy
Requires-Dist: pdoc ; extra == 'docs'
Provides-Extra: docs
Summary: Split code into semantic chunks using tree-sitter
Keywords: code,split,tokenizer,ai,nlp
Author: Xiaojing Wang <wangxj03@gmail.com>
Author-email: Xiaojing Wang <wangxj03@gmail.com>
License: MIT
Requires-Python: >=3.8
Project-URL: Source Code, https://github.com/wangxj03/code-splitter
